omnicrawlers/__init__.py
omnicrawlers/dispatcher.py
omnicrawlers/github_crawler.py
omnicrawlers/linkedin_crawler.py
omnicrawlers-0.1.0.dist-info/LICENSE
omnicrawlers-0.1.0.dist-info/METADATA
omnicrawlers-0.1.0.dist-info/WHEEL
omnicrawlers-0.1.0.dist-info/top_level.txt
omnicrawlers-0.1.0.dist-info/RECORD
