Metadata-Version: 2.1
Name: omnicrawlers
Version: 0.1.0
Summary: A Python library for crawling LinkedIn and GitHub profiles.
Home-page: https://github.com/yourusername/your_library_name
Author: Vinayak Pratap
Author-email: Vinayakpratap606@gmail.com
Classifier: Programming Language :: Python :: 3
Classifier: License :: OSI Approved :: MIT License
Classifier: Operating System :: OS Independent
Requires-Python: >=3.6
License-File: LICENSE
Requires-Dist: requests
Requires-Dist: bs4
Requires-Dist: selenium
Requires-Dist: webdriver-manager
